flaggie/__init__.py
flaggie/__main__.py
flaggie/config.py
flaggie/mangle.py
flaggie/pm.py
flaggie-0.99.8.dist-info/entry_points.txt
flaggie-0.99.8.dist-info/COPYING
flaggie-0.99.8.dist-info/WHEEL
flaggie-0.99.8.dist-info/METADATA
flaggie-0.99.8.dist-info/RECORD
