Metadata-Version: 2.1
Name: flaggie
Version: 0.99.8
Summary: CLI mangler for Portage package.* configuration files
Author-email: Michał Górny <mgorny@gentoo.org>
Requires-Python: >=3.9
Classifier: License :: OSI Approved :: MIT License
Requires-Dist: more-itertools
Requires-Dist: gentoopm >= 0.5 ; extra == "package-manager"
Requires-Dist: rich ; extra == "pretty-log"
Requires-Dist: pytest ; extra == "test"
Project-URL: Homepage, https://github.com/projg2/flaggie/
Provides-Extra: package-manager
Provides-Extra: pretty-log
Provides-Extra: test
